README.rst
setup.py
lingvoreader/__init__.py
lingvoreader/articleheading.py
lingvoreader/bitstream.py
lingvoreader/decoder.py
lingvoreader/lentable.py
lingvoreader/lsdfile.py
lingvoreader/lsdreader.py
lingvoreader/tools.py
lingvoreader.egg-info/PKG-INFO
lingvoreader.egg-info/SOURCES.txt
lingvoreader.egg-info/dependency_links.txt
lingvoreader.egg-info/entry_points.txt
lingvoreader.egg-info/requires.txt
lingvoreader.egg-info/top_level.txt
lingvoreader.egg-info/zip-safe
test/__init__.py
test/test_arg_parser.py
test/test_bitStream.py
test/test_tools.py