Metadata-Version: 1.0
Name: lingvoreader
Version: 0.2.14
Summary: Linvo 11, 12, X3, X5 and X6 lsd reader Utilities
Home-page: https://github.com/sv99/lsdreader
Author: sv99
Author-email: sv99@inbox.ru
License: UNKNOWN
Platform: any
